gsffile/__init__.py
gsffile/format.py
gsffile/py.typed
gsffile/read.py
gsffile/write.py
gsffile-0.5.4.dist-info/METADATA
gsffile-0.5.4.dist-info/WHEEL
gsffile-0.5.4.dist-info/licenses/LICENSE
gsffile-0.5.4.dist-info/RECORD
