Metadata-Version: 2.4
Name: gsffile
Version: 0.5.4
Summary: Read and write Gwyddion Simple Field files
Project-URL: Repository, https://github.com/angelo-peronio/gsffile
Project-URL: Issues, https://github.com/angelo-peronio/gsffile/issues
Project-URL: GSF format, http://gwyddion.net/documentation/user-guide-en/gsf.html
Author: Carlo Dri, Angelo Peronio
License-Expression: MIT
License-File: LICENSE
Keywords: Gwyddion,Gwyddion Simple Field,gsf
Classifier: Development Status :: 4 - Beta
Classifier: Intended Audience :: Developers
Classifier: Intended Audience :: Science/Research
Classifier: Natural Language :: English
Classifier: Operating System :: OS Independent
Classifier: Programming Language :: Python :: 3
Classifier: Programming Language :: Python :: 3.10
Classifier: Programming Language :: Python :: 3.11
Classifier: Programming Language :: Python :: 3.12
Classifier: Programming Language :: Python :: 3.13
Classifier: Programming Language :: Python :: 3.14
Classifier: Programming Language :: Python :: Implementation :: CPython
Classifier: Programming Language :: Python :: Implementation :: PyPy
Classifier: Topic :: File Formats
Classifier: Topic :: Scientific/Engineering :: Image Processing
Classifier: Typing :: Typed
Requires-Python: >=3.10
Requires-Dist: numpy>=1.24
